mdtable/__init__.py
mdtable/__main__.py
mdtable/cli.py
mdtable/mdtable.py
mdtable-0.2.dist-info/LICENSE
mdtable-0.2.dist-info/METADATA
mdtable-0.2.dist-info/WHEEL
mdtable-0.2.dist-info/entry_points.txt
mdtable-0.2.dist-info/top_level.txt
mdtable-0.2.dist-info/RECORD
