Metadata-Version: 2.1
Name: mdtable
Version: 0.2
Summary: mdtable converts csv files to markdown formatted tables
Home-page: https://github.com/mzjp2/mdtable
Author: Zain Patel
Author-email: zain.patel06@gmail.com
License: UNKNOWN
Keywords: markdown cli convert
Platform: UNKNOWN
Classifier: Programming Language :: Python :: 3
Classifier: License :: OSI Approved :: MIT License
Classifier: Operating System :: OS Independent
Requires-Python: >=3.5
Requires-Dist: click
